{
    "site": {
        "id": 15,
        "baslik": "Deneme Bonusu",
        "renk": "#FFFF00",
        "favicon": "default.png",
        "menu1": "2",
        "menu2": "3",
        "menu3": "5",
        "menu4": "https://t.me/heimdal_bonuslar",
        "sekil": "tablo",
        "mteams": "mailto:support@heimdal.com",
        "colors": "{\n  \"colors\": {\n    \"primary\": {\n      \"main\": \"#EAB308\",\n      \"dark\": \"#CA8A04\",\n      \"light\": \"#FACC15\"\n    },\n    \"background\": {\n      \"main\": \"#0F172A\",\n      \"card\": \"#1E293B\",\n      \"alt\": \"#334155\"\n    },\n    \"text\": {\n      \"main\": \"#FFFFFF\",\n      \"secondary\": \"#CBD5E1\",\n      \"muted\": \"#94A3B8\"\n    }\n  }\n}\n",
        "noticatid": 1,
        "tablosplash": 1,
        "sweepstakes": "{\"b\":[1,2,3,4]}",
        "games": "{\n    \"groups\": [\n      {\n        \"category_id\": 1,\n        \"order\": 2,\n        \"verificationimage\": \"https://img.haberkurt.com/game/story/verification.png\",\n        \"games\": [\n          {\n            \"name\": \"Aviator\",\n            \"image\": \"https://img.haberkurt.com/game/profile/aviator.gif\",\n            \"storyimage\": \"https://img.haberkurt.com/game/story/aviator.jpg\",\n            \"storytext\": \"Yüksek çarpanlı crash oyunu. Binlerce oyuncunun tercihi.\",\n            \"sticky\": false\n          },\n          {\n            \"name\": \"Sweet Bonanza\",\n            \"image\": \"https://img.haberkurt.com/game/profile/sweet.gif\",\n            \"storyimage\": \"https://img.haberkurt.com/game/story/sweet.jpg\",\n            \"storytext\": \"En popüler slot oyunu. Yüksek RTP ve büyük kazanç fırsatları.\",\n            \"sticky\": true\n          },\n          {\n            \"name\": \"Gates of Olympus\",\n            \"image\": \"https://img.haberkurt.com/game/profile/gatesof.gif\",\n            \"storyimage\": \"https://img.haberkurt.com/game/story/gatesofolympus-story.jpg\",\n            \"storytext\": \"Pragmatic Play'in en çok oynanan oyunu. Mega kazançlar seni bekliyor.\",\n            \"sticky\": true\n          },\n          {\n            \"name\": \"Big Bass\",\n            \"image\": \"https://img.haberkurt.com/game/profile/bigbass.webp\",\n            \"storyimage\": \"https://img.haberkurt.com/game/story/bigbass-story.jpg\",\n            \"storytext\": \"Balıkçı reis olma zamanı! Büyük balık yakala, cüzdanı doldur!\",\n            \"sticky\": true\n          },\n          {\n            \"name\": \"Starlight Princess\",\n            \"image\": \"https://img.haberkurt.com/game/profile/starlight.gif\",\n            \"storyimage\": \"https://img.haberkurt.com/game/story/starlightprincess-story.jpg\",\n            \"storytext\": \"Prenses yıldızları topluyor, sen de altınları topla!\",\n            \"sticky\": false\n          },\n          {\n            \"name\": \"Dog House\",\n            \"image\": \"https://img.haberkurt.com/game/profile/doghouse.webp\",\n            \"storyimage\": \"https://img.haberkurt.com/game/story/doghouse-story.jpg\",\n            \"storytext\": \"RTP %96.51, 675x çarpan. büyük ödüller getiriyor.\",\n            \"sticky\": false\n          }\n        ]\n      },\n      {\n        \"category_id\": 1,\n        \"order\": 1,\n        \"games\": [\n          {\n            \"name\": \"Canlı Blackjack\",\n            \"image\": \"https://img.haberkurt.com/game/profile/blackjack.jpg\",\n            \"storyimage\": \"https://img.haberkurt.com/game/story/blackjack.jpg\",\n            \"storytext\": \"Gerçek krupiyelerle canlı blackjack. Profesyonel oyun deneyimi.\",\n            \"sticky\": true\n          },\n          {\n            \"name\": \"Canlı Rulet\",\n            \"image\": \"https://img.haberkurt.com/game/profile/lightning-roulette.jpg\",\n            \"storyimage\": \"https://img.haberkurt.com/game/story/roulette.jpg\",\n            \"storytext\": \"Lightning Rulet ile yüksek çarpanlar. Canlı krupiye deneyimi.\",\n            \"sticky\": true\n          },\n          {\n            \"name\": \"Crazy Time\",\n            \"image\": \"https://img.haberkurt.com/game/profile/crazytime.gif\",\n            \"storyimage\": \"https://img.haberkurt.com/game/story/crazytime-story.jpg\",\n            \"storytext\": \"En popüler canlı oyun. Büyük ödül fırsatları.\",\n            \"sticky\": false\n          }\n        ]\n      }\n    ]\n  }",
        "WinnersID": 1,
        "WheelID": 1,
        "icons": "{\n  \"footer-icon\": \"https://img.haberkurt.com/icons/footer.webp\",\n  \"giveaway-icon\": \"https://img.haberkurt.com/icons/giveaway.webp\",\n  \"header-icon\": \"https://img.haberkurt.com/icons/header.webp\",\n  \"home-icon\": \"https://img.haberkurt.com/icons/home.webp\",\n  \"plus-icon\": \"https://img.haberkurt.com/icons/plus.png\",\n  \"star-icon\": \"https://img.haberkurt.com/icons/star.webp\",\n  \"telegram-icon\": \"https://img.haberkurt.com/icons/telegram.webp\",\n  \"wheel-icon\": \"https://img.haberkurt.com/icons/wheel.webp\",\n  \"win-icon\": \"https://img.haberkurt.com/icons/win.webp\",\n  \"crown-icon\": \"https://img.haberkurt.com/icons/crown.webp\",\n  \"pin\": \"https://img.haberkurt.com/icons/pin1.svg\",\n  \"pin2\": \"https://img.haberkurt.com/icons/pin2.svg\"\n}",
        "banners": "[{\"image\":\"https://rofi.io/SansCasino-logo-512x512.png\",\"href\":\"https://t.ly/sanscasino\"},{\"image\":\"https://rofi.io/Levant-logo-512x512.png\",\"href\":\"https://bit.ly/levantgiris\"},{\"image\":\"https://rofi.io/VidoBet-logo-512x512.png\",\"href\":\"https://t.ly/vidoadres\"},{\"image\":\"https://rofi.io/ikasbet-logo-515x512.png\",\"href\":\"https://ds.tc/ikasseo\"}]",
        "pinned1": 1,
        "pinned2": 2,
        "pinned3": 3,
        "pinned4": 4,
        "pinned5": 5,
        "pinned6": 6,
        "pinnedPopup": 1
    },
    "categories": [
        {
            "id": 1,
            "title": "Trend Siteler",
            "subtitle": "Oynamak istediğiniz sitenin üzerine tıklayın.",
            "icon": "fa-user",
            "order": 1,
            "boards": [
                {
                    "id": 1,
                    "baslik": "5.500 ₺",
                    "siteadi": "sanscasino",
                    "altbaslik": "Deneme Bonusu",
                    "url": "https://t.ly/sanscasino",
                    "resimurl": "https://rofi.io/SansCasino-logo-512x512.png",
                    "site_id": 1,
                    "sira": 1,
                    "catid": 1,
                    "slider": "1"
                },
                {
                    "id": 2,
                    "baslik": "4.400 ₺",
                    "siteadi": "casinolevant",
                    "altbaslik": "Deneme Bonusu",
                    "url": "https://bit.ly/levantgiris",
                    "resimurl": "https://rofi.io/Levant-logo-512x512.png",
                    "site_id": 1,
                    "sira": 2,
                    "catid": 1,
                    "slider": "1"
                },
                {
                    "id": 3,
                    "baslik": "2.500 ₺",
                    "siteadi": "vidobet",
                    "altbaslik": "Deneme Bonusu",
                    "url": "https://t.ly/vidoadres",
                    "resimurl": "https://rofi.io/VidoBet-logo-512x512.png",
                    "site_id": 1,
                    "sira": 3,
                    "catid": 1,
                    "slider": "2"
                },
                {
                    "id": 4,
                    "baslik": "2.500 ₺",
                    "siteadi": "ikasbet",
                    "altbaslik": "Deneme Bonusu",
                    "url": "https://ds.tc/ikasseo",
                    "resimurl": "https://rofi.io/ikasbet-logo-515x512.png",
                    "site_id": 1,
                    "sira": 4,
                    "catid": 1,
                    "slider": "1"
                },
                {
                    "id": 5,
                    "baslik": "4.400 ₺",
                    "siteadi": "casinolevant",
                    "altbaslik": "Deneme Bonusu",
                    "url": "https://bit.ly/levantgiris",
                    "resimurl": "https://rofi.io/Levant-logo-512x512.png",
                    "site_id": 1,
                    "sira": 6,
                    "catid": 1,
                    "slider": "2"
                },
                {
                    "id": 6,
                    "baslik": "2.500 ₺",
                    "siteadi": "vidobet",
                    "altbaslik": "Deneme Bonusu",
                    "url": "https://t.ly/vidoadres",
                    "resimurl": "https://rofi.io/VidoBet-logo-512x512.png",
                    "site_id": 1,
                    "sira": 7,
                    "catid": 1,
                    "slider": "2"
                },
                {
                    "id": 7,
                    "baslik": "2.500 ₺",
                    "siteadi": "sanscasino",
                    "altbaslik": "Deneme Bonusu",
                    "url": "https://t.ly/sanscasino",
                    "resimurl": "https://rofi.io/SansCasino-logo-512x512.png",
                    "site_id": 1,
                    "sira": 8,
                    "catid": 1,
                    "slider": "2"
                },
                {
                    "id": 8,
                    "baslik": "2.500 ₺",
                    "siteadi": "casinolevant",
                    "altbaslik": "Deneme Bonusu",
                    "url": "https://bit.ly/levantgiris",
                    "resimurl": "https://rofi.io/Levant-logo-512x512.png",
                    "site_id": 1,
                    "sira": 9,
                    "catid": 1,
                    "slider": "1"
                },
                {
                    "id": 9,
                    "baslik": "2.500 ₺",
                    "siteadi": "vidobet",
                    "altbaslik": "Deneme Bonusu",
                    "url": "https://t.ly/vidoadres",
                    "resimurl": "https://rofi.io/VidoBet-logo-512x512.png",
                    "site_id": 1,
                    "sira": 10,
                    "catid": 1,
                    "slider": "1"
                },
                {
                    "id": 10,
                    "baslik": "4.400 ₺",
                    "siteadi": "sanscasino",
                    "altbaslik": "Deneme Bonusu",
                    "url": "https://t.ly/sanscasino",
                    "resimurl": "https://rofi.io/SansCasino-logo-512x512.png",
                    "site_id": 1,
                    "sira": 11,
                    "catid": 1,
                    "slider": "1"
                },
                {
                    "id": 11,
                    "baslik": "2.500 ₺",
                    "siteadi": "ikasbet",
                    "altbaslik": "Deneme Bonusu",
                    "url": "https://ds.tc/ikasseo",
                    "resimurl": "https://rofi.io/ikasbet-logo-515x512.png",
                    "site_id": 1,
                    "sira": 4,
                    "catid": 1,
                    "slider": "1"
                }
            ]
        },
        {
            "id": 23,
            "title": "Popüler Bahis Siteleri",
            "subtitle": "Oynamak istediğiniz sitenin üzerine tıklayın.",
            "icon": "fa-user",
            "order": 2,
            "boards": [
                {
                    "id": 1,
                    "baslik": "5.500 ₺",
                    "siteadi": "sanscasino",
                    "altbaslik": "Deneme Bonusu",
                    "url": "https://t.ly/sanscasino",
                    "resimurl": "https://rofi.io/SansCasino-logo-512x512.png",
                    "site_id": 1,
                    "sira": 1,
                    "catid": 23,
                    "slider": "1"
                },
                {
                    "id": 2,
                    "baslik": "4.400 ₺",
                    "siteadi": "casinolevant",
                    "altbaslik": "Deneme Bonusu",
                    "url": "https://bit.ly/levantgiris",
                    "resimurl": "https://rofi.io/Levant-logo-512x512.png",
                    "site_id": 1,
                    "sira": 2,
                    "catid": 23,
                    "slider": "1"
                },
                {
                    "id": 3,
                    "baslik": "2.500 ₺",
                    "siteadi": "vidobet",
                    "altbaslik": "Deneme Bonusu",
                    "url": "https://t.ly/vidoadres",
                    "resimurl": "https://rofi.io/VidoBet-logo-512x512.png",
                    "site_id": 1,
                    "sira": 3,
                    "catid": 23,
                    "slider": "2"
                },
                {
                    "id": 4,
                    "baslik": "2.500 ₺",
                    "siteadi": "ikasbet",
                    "altbaslik": "Deneme Bonusu",
                    "url": "https://ds.tc/ikasseo",
                    "resimurl": "https://rofi.io/ikasbet-logo-515x512.png",
                    "site_id": 1,
                    "sira": 4,
                    "catid": 23,
                    "slider": "1"
                },
                {
                    "id": 5,
                    "baslik": "4.400 ₺",
                    "siteadi": "casinolevant",
                    "altbaslik": "Deneme Bonusu",
                    "url": "https://bit.ly/levantgiris",
                    "resimurl": "https://rofi.io/Levant-logo-512x512.png",
                    "site_id": 1,
                    "sira": 6,
                    "catid": 23,
                    "slider": "2"
                },
                {
                    "id": 6,
                    "baslik": "2.500 ₺",
                    "siteadi": "vidobet",
                    "altbaslik": "Deneme Bonusu",
                    "url": "https://t.ly/vidoadres",
                    "resimurl": "https://rofi.io/VidoBet-logo-512x512.png",
                    "site_id": 1,
                    "sira": 7,
                    "catid": 23,
                    "slider": "2"
                },
                {
                    "id": 7,
                    "baslik": "2.500 ₺",
                    "siteadi": "sanscasino",
                    "altbaslik": "Deneme Bonusu",
                    "url": "https://t.ly/sanscasino",
                    "resimurl": "https://rofi.io/SansCasino-logo-512x512.png",
                    "site_id": 1,
                    "sira": 8,
                    "catid": 23,
                    "slider": "2"
                },
                {
                    "id": 8,
                    "baslik": "2.500 ₺",
                    "siteadi": "casinolevant",
                    "altbaslik": "Deneme Bonusu",
                    "url": "https://bit.ly/levantgiris",
                    "resimurl": "https://rofi.io/Levant-logo-512x512.png",
                    "site_id": 1,
                    "sira": 9,
                    "catid": 23,
                    "slider": "1"
                },
                {
                    "id": 9,
                    "baslik": "2.500 ₺",
                    "siteadi": "vidobet",
                    "altbaslik": "Deneme Bonusu",
                    "url": "https://t.ly/vidoadres",
                    "resimurl": "https://rofi.io/VidoBet-logo-512x512.png",
                    "site_id": 1,
                    "sira": 10,
                    "catid": 23,
                    "slider": "1"
                },
                {
                    "id": 10,
                    "baslik": "4.400 ₺",
                    "siteadi": "sanscasino",
                    "altbaslik": "Deneme Bonusu",
                    "url": "https://t.ly/sanscasino",
                    "resimurl": "https://rofi.io/SansCasino-logo-512x512.png",
                    "site_id": 1,
                    "sira": 11,
                    "catid": 23,
                    "slider": "1"
                },
                {
                    "id": 11,
                    "baslik": "2.500 ₺",
                    "siteadi": "ikasbet",
                    "altbaslik": "Deneme Bonusu",
                    "url": "https://ds.tc/ikasseo",
                    "resimurl": "https://rofi.io/ikasbet-logo-515x512.png",
                    "site_id": 1,
                    "sira": 4,
                    "catid": 23,
                    "slider": "1"
                }
            ]
        }
    ],
    "texts": {
        "header": [
            {
                "id": 8,
                "baslik": "ŞansCasino 2.500 TL Bonus",
                "url": "https://t.ly/sanscasino",
                "tip": "header",
                "durum": 1
            }
        ],
        "footer": [
            {
                "id": 1,
                "baslik": "ŞansCasino 2.500 TL Bonus",
                "url": "https://t.ly/sanscasino",
                "tip": "footer",
                "durum": 1
            }
        ]
    },
    "popups": {
        "popup1": [
            {
                "id": 1,
                "resimurl": "https://rofi.io/SansCasino-logo-512x512.png",
                "url": "https://t.ly/sanscasino",
                "popuporder": 1,
                "durum": 1
            },
            {
                "id": 2,
                "resimurl": "https://rofi.io/Levant-logo-512x512.png",
                "url": "https://bit.ly/levantgiris",
                "popuporder": 1,
                "durum": 1
            },
            {
                "id": 3,
                "resimurl": "https://rofi.io/VidoBet-logo-512x512.png",
                "url": "https://t.ly/vidoadres",
                "popuporder": 1,
                "durum": 1
            }
        ],
        "popup2": [
            {
                "id": 4,
                "resimurl": "https://rofi.io/ikasbet-logo-515x512.png",
                "url": "https://ds.tc/ikasseo",
                "popuporder": 2,
                "durum": 1
            }
        ]
    },
    "big": [
        {
            "id": 1,
            "resimurl": "https://rofi.io/SansCasino-logo-512x512.png",
            "url": "https://t.ly/sanscasino",
            "groupp": 1,
            "durum": 1
        },
        {
            "id": 2,
            "resimurl": "https://rofi.io/Levant-logo-512x512.png",
            "url": "https://bit.ly/levantgiris",
            "groupp": 2,
            "durum": 1
        },
        {
            "id": 3,
            "resimurl": "https://rofi.io/VidoBet-logo-512x512.png",
            "url": "https://t.ly/vidoadres",
            "groupp": 2,
            "durum": 1
        }
    ]
}